Hardware Description Language Principle and Application/硬件描述语言与应用-大作业-钱煜-3180103948/32位除法器/div.v
module DIVUN_32(clk,reset,enable,dividend,divisor0,quotient,remainder);
input clk; 
input reset; 
input enable; 
input [31:0] dividend;
input [31:0] divisor0;
output reg [31:0] quotient;
output reg [31:0] remainder;

reg [1:0] state,next_state;//state:0:wait 1:get MSB and f 2:initialize  3:calculate
reg [4:0] iteration,f,L1,L2;
reg [31:0] divisor;
reg [31:0] cmp_dividend,cmp_divisor; 
reg r1,r2,r3,r4;
reg [31:0] r5;

always @(posedge clk)
	begin
	
	
	if (!reset) 
			begin
			quotient=0;
			remainder=0;
			next_state=1;		
		    end
	else 
	
	begin
	
	if (enable)
	begin
		state=next_state;
		case (state)
		
		2'b00:begin  
	
				if (cmp_dividend!==dividend || divisor0!==cmp_divisor) next_state=1;
				else next_state=0;
		      end
		
		2'b01:
		  begin
			if (dividend[31]) L1=32;
                else if (dividend[30]) L1=31;
                else if (dividend[29]) L1=30;
                else if (dividend[28]) L1=29;
                else if (dividend[27]) L1=28;
                else if (dividend[26]) L1=27;
                else if (dividend[25]) L1=26;
                else if (dividend[24]) L1=25;
                else if (dividend[23]) L1=24;
                else if (dividend[22]) L1=23;
                else if (dividend[21]) L1=22;
                else if (dividend[20]) L1=21;
                else if (dividend[19]) L1=20;
                else if (dividend[18]) L1=19;
                else if (dividend[17]) L1=18;
                else if (dividend[16]) L1=17;
                else if (dividend[15]) L1=16;
                else if (dividend[14]) L1=15;
                else if (dividend[13]) L1=14;
                else if (dividend[12]) L1=13;
                else if (dividend[11]) L1=12;
                else if (dividend[10]) L1=11;
                else if (dividend[9]) L1=10;
                else if (dividend[8]) L1=9;
                else if (dividend[7]) L1=8;
                else if (dividend[6]) L1=7;
                else if (dividend[5]) L1=6;
                else if (dividend[4]) L1=5;
                else if (dividend[3]) L1=4;
                else if (dividend[2]) L1=3;
                else if (dividend[1]) L1=2;
		else if (dividend[0]) L1=1;
                else L1=0;
				
			if (divisor0[31]) L2=32;
                else if (divisor0[30]) L2=31;
                else if (divisor0[29]) L2=30;
                else if (divisor0[28]) L2=29;
                else if (divisor0[27]) L2=28;
                else if (divisor0[26]) L2=27;
                else if (divisor0[25]) L2=26;
                else if (divisor0[24]) L2=25;
                else if (divisor0[23]) L2=24;
                else if (divisor0[22]) L2=23;
                else if (divisor0[21]) L2=22;
                else if (divisor0[20]) L2=21;
                else if (divisor0[19]) L2=20;
                else if (divisor0[18]) L2=19;
                else if (divisor0[17]) L2=18;
                else if (divisor0[16]) L2=17;
                else if (divisor0[15]) L2=16;
                else if (divisor0[14]) L2=15;
                else if (divisor0[13]) L2=14;
                else if (divisor0[12]) L2=13;
                else if (divisor0[11]) L2=12;
                else if (divisor0[10]) L2=11;
                else if (divisor0[9]) L2=10;
                else if (divisor0[8]) L2=9;
                else if (divisor0[7]) L2=8;
                else if (divisor0[6]) L2=7;
                else if (divisor0[5]) L2=6;
                else if (divisor0[4]) L2=5;
                else if (divisor0[3]) L2=4;
                else if (divisor0[2]) L2=3;
                else if (divisor0[1]) L2=2;
		else if (divisor0[0]) L2=1;
                else L2=0;

                	if (!L2) begin
				next_state=0;
				remainder=32'b1111111111111111;
				quotient=32'b1111111111111111;
				cmp_dividend=dividend;				
				cmp_divisor=divisor0;
				end
				
			else
				begin		
				f=L1-L2;
				next_state=2;
				end
		  end
		  
		2'b10:
		  begin
			remainder=dividend;
			cmp_dividend=dividend;
			cmp_divisor=divisor0;
			divisor=divisor0;
			divisor=divisor<<f;
			quotient=0;
			iteration=f+1;
		    next_state=3;
		  end
		
		2'b11:
		  begin
			if (!iteration)
				begin
					
					next_state=0;
				
				end
				
			else
				begin
				
				    if (remainder>=divisor) 
						begin
						quotient=(quotient<<1)+1;
						remainder=remainder-divisor;
						divisor=divisor>>1;
						end
					else
						begin
						quotient=(quotient<<1)+0;
						remainder=remainder;
						divisor=divisor>>1;
						end
					
					iteration=iteration-1;
					next_state=3;
				end
		  
		  end


		endcase

	
	end
	else next_state=next_state;
	end
	end
	
endmodule

Hardware Description Language Principle and Application/硬件描述语言与应用-大作业-钱煜-3180103948/32位除法器/div_tb.v
//`timescale 1ns / 1ps
module DIVUN_32_tb;
parameter delay=10;

reg clk; 
reg reset; 
reg enable; 
reg [31:0] dividend;
reg [31:0] divisor;
wire [31:0] quotient;
wire [31:0] remainder;


initial
begin
$dumpfile("div.vcd");
$dumpvars();
#300 $finish;
end



DIVUN_32  DIVUN_32_test(.clk(clk),
					 .reset(reset),
					 .enable(enable),
					 .dividend(dividend),
					 .divisor0(divisor),
					 .quotient(quotient),
					 .remainder(remainder));

	initial 
	  begin

		// Initialize Inputs
		clk = 0;
		reset = 1;
		enable = 0;
		dividend = 0;
		divisor = 0;

		// 
		#(delay*5)  reset=0;
		#(delay*5)  reset=1;enable=1;dividend=183;divisor=14;
		#(delay*5)  dividend=115;divisor=1;
		#(delay*5)  dividend=13;divisor=0;
		#(delay*5)  dividend=153;divisor=1;
	    #(delay*10) $stop;
         
    end

	//clock
  always 		#(delay/5) clk=~clk;

//`ifdef FSDB
//initial begin
//	$fsdbDumpfile("tb_div.fsdb");
//	$fsdbDumpvars;
//end
//`endif
endmodule

Hardware Description Language Principle and Application/硬件描述语言与应用-大作业-钱煜-3180103948/32位除法器/div.vcd
$date
	Mon Nov  2 14:46:37 2020
$end

$version
	Synopsys VCS version G-2012.09
$end

$timescale
	1s
$end

$comment Csum: 1 b4e7992c36b5b68e $end


$scope module DIVUN_32_tb $end
$var reg 1 ! clk $end
$var reg 1 " reset $end
$var reg 1 # enable $end
$var reg 32 $ dividend [31:0] $end
$var reg 32 % divisor [31:0] $end
$var wire 1 & quotient [31] $end
$var wire 1 ' quotient [30] $end
$var wire 1 ( quotient [29] $end
$var wire 1 ) quotient [28] $end
$var wire 1 * quotient [27] $end
$var wire 1 + quotient [26] $end
$var wire 1 , quotient [25] $end
$var wire 1 - quotient [24] $end
$var wire 1 . quotient [23] $end
$var wire 1 / quotient [22] $end
$var wire 1 0 quotient [21] $end
$var wire 1 1 quotient [20] $end
$var wire 1 2 quotient [19] $end
$var wire 1 3 quotient [18] $end
$var wire 1 4 quotient [17] $end
$var wire 1 5 quotient [16] $end
$var wire 1 6 quotient [15] $end
$var wire 1 7 quotient [14] $end
$var wire 1 8 quotient [13] $end
$var wire 1 9 quotient [12] $end
$var wire 1 : quotient [11] $end
$var wire 1 ; quotient [10] $end
$var wire 1 < quotient [9] $end
$var wire 1 = quotient [8] $end
$var wire 1 > quotient [7] $end
$var wire 1 ? quotient [6] $end
$var wire 1 @ quotient [5] $end
$var wire 1 A quotient [4] $end
$var wire 1 B quotient [3] $end
$var wire 1 C quotient [2] $end
$var wire 1 D quotient [1] $end
$var wire 1 E quotient [0] $end
$var wire 1 F remainder [31] $end
$var wire 1 G remainder [30] $end
$var wire 1 H remainder [29] $end
$var wire 1 I remainder [28] $end
$var wire 1 J remainder [27] $end
$var wire 1 K remainder [26] $end
$var wire 1 L remainder [25] $end
$var wire 1 M remainder [24] $end
$var wire 1 N remainder [23] $end
$var wire 1 O remainder [22] $end
$var wire 1 P remainder [21] $end
$var wire 1 Q remainder [20] $end
$var wire 1 R remainder [19] $end
$var wire 1 S remainder [18] $end
$var wire 1 T remainder [17] $end
$var wire 1 U remainder [16] $end
$var wire 1 V remainder [15] $end
$var wire 1 W remainder [14] $end
$var wire 1 X remainder [13] $end
$var wire 1 Y remainder [12] $end
$var wire 1 Z remainder [11] $end
$var wire 1 [ remainder [10] $end
$var wire 1 \ remainder [9] $end
$var wire 1 ] remainder [8] $end
$var wire 1 ^ remainder [7] $end
$var wire 1 _ remainder [6] $end
$var wire 1 ` remainder [5] $end
$var wire 1 a remainder [4] $end
$var wire 1 b remainder [3] $end
$var wire 1 c remainder [2] $end
$var wire 1 d remainder [1] $end
$var wire 1 e remainder [0] $end

$scope module DIVUN_32_test $end
$var wire 1 ! clk $end
$var wire 1 " reset $end
$var wire 1 # enable $end
$var wire 32 $ dividend [31:0] $end
$var wire 32 % divisor0 [31:0] $end
$var reg 32 f quotient [31:0] $end
$var reg 32 g remainder [31:0] $end
$var reg 2 h state [1:0] $end
$var reg 2 i next_state [1:0] $end
$var reg 5 j iteration [4:0] $end
$var reg 5 k f [4:0] $end
$var reg 5 l L1 [4:0] $end
$var reg 5 m L2 [4:0] $end
$var reg 32 n divisor [31:0] $end
$var reg 32 o cmp_dividend [31:0] $end
$var reg 32 p cmp_divisor [31:0] $end
$var reg 1 q r1 $end
$var reg 1 r r2 $end
$var reg 1 s r3 $end
$var reg 1 t r4 $end
$var reg 32 u r5 [31:0] $end
$upscope $end

$upscope $end

$enddefinitions $end

#0
$dumpvars
0!
0#
xE
x;
x:
x9
x8
x7
x6
x5
x4
x3
x2
xD
x1
x0
x/
x.
x-
x,
x+
x*
x)
x(
xC
x'
x&
xB
xA
x@
x?
x>
x=
x<
xq
xr
xs
xt
xe
x[
xZ
xY
xX
xW
xV
xU
xT
xS
xR
xd
xQ
xP
xO
xN
xM
xL
xK
xJ
xI
xH
xc
xG
xF
xb
xa
x`
x_
x^
x]
x\
1"
bxxxxxxxxxxxxxxxxxxxxxxxxxxxxxxxx n
bxxxxx l
bxxxxx m
bxxxxxxxxxxxxxxxxxxxxxxxxxxxxxxxx o
bxxxxxxxxxxxxxxxxxxxxxxxxxxxxxxxx p
b00000000000000000000000000000000 $
b00000000000000000000000000000000 %
bxxxxx k
bxxxxx j
bxx i
bxxxxxxxxxxxxxxxxxxxxxxxxxxxxxxxx f
bxxxxxxxxxxxxxxxxxxxxxxxxxxxxxxxx u
bxxxxxxxxxxxxxxxxxxxxxxxxxxxxxxxx g
bxx h
$end
#2
1!
#4
0!
#6
1!
#8
0!
#10
1!
#12
0!
#14
1!
#16
0!
#18
1!
#20
0!
#22
1!
#24
0!
#26
1!
#28
0!
#30
1!
#32
0!
#34
1!
#36
0!
#38
1!
#40
0!
#42
1!
#44
0!
#46
1!
#48
0!
#50
0"
1!
b00000000000000000000000000000000 f
0&
0'
0(
0)
0*
0+
0,
0-
0.
0/
00
01
02
03
04
05
06
07
08
09
0:
0;
0<
0=
0>
0?
0@
0A
0B
0C
0D
0E
b00000000000000000000000000000000 g
0F
0G
0H
0I
0J
0K
0L
0M
0N
0O
0P
0Q
0R
0S
0T
0U
0V
0W
0X
0Y
0Z
0[
0\
0]
0^
0_
0`
0a
0b
0c
0d
0e
b01 i
#52
0!
#54
1!
#56
0!
#58
1!
#60
0!
#62
1!
#64
0!
#66
1!
#68
0!
#70
1!
#72
0!
#74
1!
#76
0!
#78
1!
#80
0!
#82
1!
#84
0!
#86
1!
#88
0!
#90
1!
#92
0!
#94
1!
#96
0!
#98
1!
#100
1"
1#
b00000000000000000000000010110111 $
b00000000000000000000000000001110 %
0!
#102
1!
b01 h
b01000 l
b00100 m
b00100 k
b10 i
#104
0!
#106
1!
b10 h
b00000000000000000000000010110111 g
1^
1`
1a
1c
1d
1e
b00000000000000000000000010110111 o
b00000000000000000000000000001110 p
b00000000000000000000000011100000 n
b00101 j
b11 i
#108
0!
#110
1!
b11 h
b00000000000000000000000001110000 n
b00100 j
#112
0!
#114
1!
b00000000000000000000000000000001 f
1E
b00000000000000000000000001000111 g
0^
1_
0`
0a
b00000000000000000000000000111000 n
b00011 j
#116
0!
#118
1!
b00000000000000000000000000000011 f
1D
b00000000000000000000000000001111 g
0_
1b
b00000000000000000000000000011100 n
b00010 j
#120
0!
#122
1!
b00000000000000000000000000000110 f
1C
0E
b00000000000000000000000000001110 n
b00001 j
#124
0!
#126
1!
b00000000000000000000000000001101 f
1B
0D
1E
b00000000000000000000000000000001 g
0b
0c
0d
b00000000000000000000000000000111 n
b00000 j
#128
0!
#130
1!
b00 i
#132
0!
#134
1!
b00 h
#136
0!
#138
1!
#140
0!
#142
1!
#144
0!
#146
1!
#148
0!
#150
b00000000000000000000000001110011 $
b00000000000000000000000000000001 %
1!
b01 i
#152
0!
#154
1!
b01 h
b00111 l
b00001 m
b00110 k
b10 i
#156
0!
#158
1!
b10 h
b00000000000000000000000001110011 g
1_
1`
1a
1d
b00000000000000000000000001110011 o
b00000000000000000000000000000001 p
b00000000000000000000000001000000 n
b00000000000000000000000000000000 f
0B
0C
0E
b00111 j
b11 i
#160
0!
#162
1!
b11 h
b00000000000000000000000000000001 f
1E
b00000000000000000000000000110011 g
0_
b00000000000000000000000000100000 n
b00110 j
#164
0!
#166
1!
b00000000000000000000000000000011 f
1D
b00000000000000000000000000010011 g
0`
b00000000000000000000000000010000 n
b00101 j
#168
0!
#170
1!
b00000000000000000000000000000111 f
1C
b00000000000000000000000000000011 g
0a
b00000000000000000000000000001000 n
b00100 j
#172
0!
#174
1!
b00000000000000000000000000001110 f
1B
0E
b00000000000000000000000000000100 n
b00011 j
#176
0!
#178
1!
b00000000000000000000000000011100 f
1A
0D
b00000000000000000000000000000010 n
b00010 j
#180
0!
#182
1!
b00000000000000000000000000111001 f
1@
0C
1E
b00000000000000000000000000000001 g
0d
b00000000000000000000000000000001 n
b00001 j
#184
0!
#186
1!
b00000000000000000000000001110011 f
1?
0B
1D
b00000000000000000000000000000000 g
0e
b00000000000000000000000000000000 n
b00000 j
#188
0!
#190
1!
b00 i
#192
0!
#194
1!
b00 h
#196
0!
#198
1!
#200
b00000000000000000000000000001101 $
b00000000000000000000000000000000 %
0!
#202
1!
b01 i
#204
0!
#206
1!
b01 h
b00100 l
b00000 m
b00 i
b00000000000000001111111111111111 g
1V
1W
1X
1Y
1Z
1[
1\
1]
1^
1_
1`
1a
1b
1c
1d
1e
b00000000000000001111111111111111 f
16
17
18
19
1:
1;
1<
1=
1>
1B
1C
b00000000000000000000000000001101 o
b00000000000000000000000000000000 p
#208
0!
#210
1!
b00 h
#212
0!
#214
1!
#216
0!
#218
1!
#220
0!
#222
1!
#224
0!
#226
1!
#228
0!
#230
1!
#232
0!
#234
1!
#236
0!
#238
1!
#240
0!
#242
1!
#244
0!
#246
1!
#248
0!
#250
b00000000000000000000000010011001 $
b00000000000000000000000000000001 %
1!
b01 i
#252
0!
#254
1!
b01 h
b01000 l
b00001 m
b00111 k
b10 i
#256
0!
#258
1!
b10 h
b00000000000000000000000010011001 g
0V
0W
0X
0Y
0Z
0[
0\
0]
0_
0`
0c
0d
b00000000000000000000000010011001 o
b00000000000000000000000000000001 p
b00000000000000000000000010000000 n
b00000000000000000000000000000000 f
06
07
08
09
0:
0;
0<
0=
0>
0?
0@
0A
0B
0C
0D
0E
b01000 j
b11 i
#260
0!
#262
1!
b11 h
b00000000000000000000000000000001 f
1E
b00000000000000000000000000011001 g
0^
b00000000000000000000000001000000 n
b00111 j
#264
0!
#266
1!
b00000000000000000000000000000010 f
1D
0E
b00000000000000000000000000100000 n
b00110 j
#268
0!
#270
1!
b00000000000000000000000000000100 f
1C
0D
b00000000000000000000000000010000 n
b00101 j
#272
0!
#274
1!
b00000000000000000000000000001001 f
1B
0C
1E
b00000000000000000000000000001001 g
0a
b00000000000000000000000000001000 n
b00100 j
#276
0!
#278
1!
b00000000000000000000000000010011 f
1A
0B
1D
b00000000000000000000000000000001 g
0b
b00000000000000000000000000000100 n
b00011 j
#280
0!
#282
1!
b00000000000000000000000000100110 f
1@
0A
1C
0E
b00000000000000000000000000000010 n
b00010 j
#284
0!
#286
1!
b00000000000000000000000001001100 f
1?
0@
1B
0D
b00000000000000000000000000000001 n
b00001 j
#288
0!
#290
1!
b00000000000000000000000010011001 f
1>
0?
1A
0C
1E
b00000000000000000000000000000000 g
0e
b00000000000000000000000000000000 n
b00000 j
#292
0!
#294
1!
b00 i
#296
0!
#298
1!
b00 h
